sessionless/__init__.py
sessionless/modelsecp256k1.py
test/__init__.py
test/test_modelsecp256k1.py
sessionless-0.0.4.dist-info/METADATA
sessionless-0.0.4.dist-info/WHEEL
sessionless-0.0.4.dist-info/top_level.txt
sessionless-0.0.4.dist-info/RECORD
