Metadata-Version: 2.1
Name: sessionless
Version: 0.0.4
Summary: Sessionless is an attempt to make authentication handling easier for developers without traditional sessions.
Author: Sessionless Team
Author-email: zach@planetnine.app
Keywords: authentication,cryptography,authenticate
Classifier: Development Status :: 3 - Alpha
Classifier: Intended Audience :: Developers
Classifier: Programming Language :: Python :: 3
Classifier: Operating System :: MacOS :: MacOS X
Classifier: Operating System :: Microsoft :: Windows
Requires-Dist: secp256k1
Requires-Dist: uuid
